powfile/__init__.py
powfile/powfile.py
powfile-0.1.0.dist-info/AUTHORS.rst
powfile-0.1.0.dist-info/LICENSE
powfile-0.1.0.dist-info/METADATA
powfile-0.1.0.dist-info/WHEEL
powfile-0.1.0.dist-info/entry_points.txt
powfile-0.1.0.dist-info/top_level.txt
powfile-0.1.0.dist-info/RECORD
