Metadata-Version: 2.1
Name: powfile
Version: 0.1.0
Summary: A quick script to help you switch up powershell profile files, and reset them back to normal.
Home-page: https://github.com/hithismani/powfile
Author: Mani Kumar
Author-email: hi@manikumar.in
License: MIT license
Keywords: powfile
Platform: UNKNOWN
Classifier: Development Status :: 2 - Pre-Alpha
Classifier: Intended Audience :: Developers
Classifier: License :: OSI Approved :: MIT License
Classifier: Natural Language :: English
Classifier: Programming Language :: Python :: 3
Classifier: Programming Language :: Python :: 3.5
Classifier: Programming Language :: Python :: 3.6
Classifier: Programming Language :: Python :: 3.7
Classifier: Programming Language :: Python :: 3.8
Requires-Python: >=3.5
